django_probes/__init__.py
django_probes/management/__init__.py
django_probes/management/commands/__init__.py
django_probes/management/commands/wait_for_database.py
django_probes-1.7.0.dist-info/LICENSE
django_probes-1.7.0.dist-info/METADATA
django_probes-1.7.0.dist-info/WHEEL
django_probes-1.7.0.dist-info/top_level.txt
django_probes-1.7.0.dist-info/RECORD
