Metadata-Version: 2.1
Name: django-probes
Version: 1.7.0
Summary: Make Django wait until database is ready. Probes for Docker and Kubernetes.
Home-page: https://github.com/painless-software/django-probes
Author: Peter Bittner
Author-email: django@bittner.it
Keywords: django,database,probes,docker,kubernetes
Classifier: Development Status :: 5 - Production/Stable
Classifier: Intended Audience :: Developers
Classifier: License :: OSI Approved :: BSD License
Classifier: Framework :: Django
Classifier: Framework :: Django :: 3.2
Classifier: Framework :: Django :: 4.0
Classifier: Framework :: Django :: 4.1
Classifier: Programming Language :: Python
Classifier: Programming Language :: Python :: 3.6
Classifier: Programming Language :: Python :: 3.7
Classifier: Programming Language :: Python :: 3.8
Classifier: Programming Language :: Python :: 3.9
Classifier: Programming Language :: Python :: 3.10
License-File: LICENSE
